{
  "db_name": "PostgreSQL",
  "query": "\n        SELECT COUNT(*) AS \"count!: i64\"\n        FROM assignments a\n        WHERE a.season_id = $1 AND a.receipt_status = 'no_response'\n        ",
  "describe": {
    "columns": [
      {
        "ordinal": 0,
        "name": "count!: i64",
        "type_info": "Int8"
      }
    ],
    "parameters": {
      "Left": [
        "Uuid"
      ]
    },
    "nullable": [
      null
    ]
  },
  "hash": "cae7d2d073ebeed5ad2d56509a6181019a1e288eeafe6d2b4903b10b50f0eafe"
}
